.coveragerc
.readthedocs.yml
.travis.yml
AUTHORS.txt
CHANGES.rst
COPYRIGHT.txt
LICENSE.txt
MANIFEST.in
Makefile
README.rst
setup.cfg
setup.py
tox.ini
docs/Makefile
docs/README.rst
docs/api.rst
docs/changes.rst
docs/conf.py
docs/index.rst
docs/make.bat
docs/requirements.txt
docs/api/immutable.rst
docs/api/interfaces.rst
docs/api/pjpersist.rst
docs/api/revisioned.rst
src/shoobx/__init__.py
src/shoobx.immutable.egg-info/PKG-INFO
src/shoobx.immutable.egg-info/SOURCES.txt
src/shoobx.immutable.egg-info/dependency_links.txt
src/shoobx.immutable.egg-info/namespace_packages.txt
src/shoobx.immutable.egg-info/not-zip-safe
src/shoobx.immutable.egg-info/requires.txt
src/shoobx.immutable.egg-info/top_level.txt
src/shoobx/immutable/__init__.py
src/shoobx/immutable/immutable.py
src/shoobx/immutable/interfaces.py
src/shoobx/immutable/pjpersist.py
src/shoobx/immutable/revisioned.py
src/shoobx/immutable/tests/__init__.py
src/shoobx/immutable/tests/test_immutable.py
src/shoobx/immutable/tests/test_pjpersist.py
src/shoobx/immutable/tests/test_revisioned.py