Metadata-Version: 2.1
Name: shoobx.immutable
Version: 1.4.0
Summary: Immutable Types
Home-page: http://pypi.python.org/pypi/shoobx.immutable
Author: Shoobx, Inc.
Author-email: dev@shoobx.com
License: ZPL 2.1
Keywords: immutable revisioned pjpersist
Platform: UNKNOWN
Classifier: Development Status :: 5 - Production/Stable
Classifier: Intended Audience :: Developers
Classifier: License :: OSI Approved :: Zope Public License
Classifier: Programming Language :: Python
Classifier: Programming Language :: Python :: 3
Classifier: Programming Language :: Python :: 3.7
Classifier: Programming Language :: Python :: Implementation :: CPython
Classifier: Natural Language :: English
Classifier: Operating System :: OS Independent
Provides-Extra: docs
Provides-Extra: test
Provides-Extra: pjpersist
